IGNORE.txt
MANIFEST.in
README.txt
setup.py
collective/__init__.py
collective/__init__.pyc
collective.js.jqshorten.egg-info/PKG-INFO
collective.js.jqshorten.egg-info/SOURCES.txt
collective.js.jqshorten.egg-info/dependency_links.txt
collective.js.jqshorten.egg-info/entry_points.txt
collective.js.jqshorten.egg-info/namespace_packages.txt
collective.js.jqshorten.egg-info/not-zip-safe
collective.js.jqshorten.egg-info/requires.txt
collective.js.jqshorten.egg-info/top_level.txt
collective/js/__init__.py
collective/js/__init__.pyc
collective/js/jqshorten/__init__.py
collective/js/jqshorten/configure.zcml
collective/js/jqshorten/jquery.shorten.js
collective/js/jqshorten/version.txt
collective/js/jqshorten/profiles/default/jsregistry.xml
collective/js/jqshorten/profiles/default/metadata.xml
docs/HISTORY.txt