Metadata-Version: 1.0
Name: collective.js.jqshorten
Version: 1.0a2
Summary: jquery.shorten plugin (Maintainer Elio Schmutz)
Home-page: https://github.com/MarcDiethelm/jQuery-Shorten
Author: Elio Schmutz, 4teamwork GmbH
Author-email: mailto:info@4teamwork.ch
License: GPL2
Keywords: jquery shorten
Platform: UNKNOWN
Classifier: Programming Language :: Python
Classifier: Topic :: Software Development :: Libraries :: Python Modules
